HDL/rtl/phase_accu.vhd
library ieee;
use ieee.std_logic_1164.all;
use ieee.numeric_std.all;

entity phase_accu is
    generic(
        ACCU_WIDTH : integer := 16;
        PHASE_INCR : integer := 5243 -- 10Mhz with a 125Mhz clk
    );

    port (
        clk      : in std_logic;
        reset    : in std_logic;
        accu_out : out std_logic_vector(ACCU_WIDTH - 1 downto 0)
    );
end phase_accu;

architecture rtl of phase_accu is
    signal accu : signed(ACCU_WIDTH - 1 downto 0) := (others => '0');
begin
    
    process(clk)
    begin
        if rising_edge(clk) then
            if reset = '1' then
                accu <= (others => '0');
            else
                accu <= accu + PHASE_INCR;
            end if;
        end if;

    accu_out <= std_logic_vector(accu);
    end process;

end architecture;

HDL/tb/phase_accu_tb.vhd
library ieee;
use ieee.std_logic_1164.all;
use ieee.numeric_std.all;

entity phase_accu_tb is
end entity phase_accu_tb;

architecture sim of phase_accu_tb is

    constant CLK_PERIOD : time    := 10 ns;
    constant ACCU_WIDTH : integer := 16;
    constant PHASE_INCR : integer := 5243;

    signal clk   : std_logic := '0';
    signal reset : std_logic := '0';

    signal phase_accu_out : std_logic_vector(ACCU_WIDTH - 1 downto 0);

begin

    -- Device under test
    dut : entity work.phase_accu
        generic map (
            ACCU_WIDTH => ACCU_WIDTH,
            PHASE_INCR => PHASE_INCR
        )
        port map (
            clk      => clk,
            reset    => reset,
            accu_out => phase_accu_out
        );

    -- Clock generator
    clk_process : process
    begin
        while true loop
            clk <= '0';
            wait for CLK_PERIOD / 2;

            clk <= '1';
            wait for CLK_PERIOD / 2;
        end loop;
    end process;

    -- Input stimulus
    stimulus_process : process
    begin

        -- Hold reset active
        reset <= '1';
        wait for 2 * CLK_PERIOD;

        -- Release reset near a clock edge
        wait until falling_edge(clk);
        reset <= '0';

        wait;

    end process;

end architecture sim;

HDL/waveform.vcd
$date
  Sun Jul 26 23:41:24 2026
$end
$version
  GHDL v0
$end
$timescale
  1 fs
$end
$scope module standard $end
$upscope $end
$scope module std_logic_1164 $end
$upscope $end
$scope module numeric_std $end
$upscope $end
$scope module phase_accu_tb $end
$var reg 1 ! clk $end
$var reg 1 " reset $end
$var reg 16 # phase_accu_out[15:0] $end
$scope module dut $end
$var reg 1 $ clk $end
$var reg 1 % reset $end
$var reg 16 & accu_out[15:0] $end
$var reg 16 ' accu[15:0] $end
$upscope $end
$upscope $end
$enddefinitions $end
#0
0!
1"
b0000000000000000 #
0$
1%
b0000000000000000 &
b0000000000000000 '
#5000000
1!
1$
#10000000
0!
0$
#15000000
1!
1$
#20000000
0!
0"
0$
0%
#25000000
1!
1$
b0001010001111011 '
#30000000
0!
b0001010001111011 #
0$
b0001010001111011 &
#35000000
1!
1$
b0010100011110110 '
#40000000
0!
b0010100011110110 #
0$
b0010100011110110 &
#45000000
1!
1$
b0011110101110001 '
#50000000
0!
b0011110101110001 #
0$
b0011110101110001 &
#55000000
1!
1$
b0101000111101100 '
#60000000
0!
b0101000111101100 #
0$
b0101000111101100 &
#65000000
1!
1$
b0110011001100111 '
#70000000
0!
b0110011001100111 #
0$
b0110011001100111 &
#75000000
1!
1$
b0111101011100010 '
#80000000
0!
b0111101011100010 #
0$
b0111101011100010 &
#85000000
1!
1$
b1000111101011101 '
#90000000
0!
b1000111101011101 #
0$
b1000111101011101 &
#95000000
1!
1$
b1010001111011000 '
#100000000
0!
b1010001111011000 #
0$
b1010001111011000 &
#105000000
1!
1$
b1011100001010011 '
#110000000
0!
b1011100001010011 #
0$
b1011100001010011 &
#115000000
1!
1$
b1100110011001110 '
#120000000
0!
b1100110011001110 #
0$
b1100110011001110 &
#125000000
1!
1$
b1110000101001001 '
#130000000
0!
b1110000101001001 #
0$
b1110000101001001 &
#135000000
1!
1$
b1111010111000100 '
#140000000
0!
b1111010111000100 #
0$
b1111010111000100 &
#145000000
1!
1$
b0000101000111111 '
#150000000
0!
b0000101000111111 #
0$
b0000101000111111 &
#155000000
1!
1$
b0001111010111010 '
#160000000
0!
b0001111010111010 #
0$
b0001111010111010 &
#165000000
1!
1$
b0011001100110101 '
#170000000
0!
b0011001100110101 #
0$
b0011001100110101 &
#175000000
1!
1$
b0100011110110000 '
#180000000
0!
b0100011110110000 #
0$
b0100011110110000 &
#185000000
1!
1$
b0101110000101011 '
#190000000
0!
b0101110000101011 #
0$
b0101110000101011 &
#195000000
1!
1$
b0111000010100110 '
#200000000
0!
b0111000010100110 #
0$
b0111000010100110 &
#205000000
1!
1$
b1000010100100001 '
#210000000
0!
b1000010100100001 #
0$
b1000010100100001 &
#215000000
1!
1$
b1001100110011100 '
#220000000
0!
b1001100110011100 #
0$
b1001100110011100 &
#225000000
1!
1$
b1010111000010111 '
#230000000
0!
b1010111000010111 #
0$
b1010111000010111 &
#235000000
1!
1$
b1100001010010010 '
#240000000
0!
b1100001010010010 #
0$
b1100001010010010 &
#245000000
1!
1$
b1101011100001101 '
#250000000
0!
b1101011100001101 #
0$
b1101011100001101 &
#255000000
1!
1$
b1110101110001000 '
#260000000
0!
b1110101110001000 #
0$
b1110101110001000 &
#265000000
1!
1$
b0000000000000011 '
#270000000
0!
b0000000000000011 #
0$
b0000000000000011 &
#275000000
1!
1$
b0001010001111110 '
#280000000
0!
b0001010001111110 #
0$
b0001010001111110 &
#285000000
1!
1$
b0010100011111001 '
#290000000
0!
b0010100011111001 #
0$
b0010100011111001 &
#295000000
1!
1$
b0011110101110100 '
#300000000
0!
b0011110101110100 #
0$
b0011110101110100 &
#305000000
1!
1$
b0101000111101111 '
#310000000
0!
b0101000111101111 #
0$
b0101000111101111 &
#315000000
1!
1$
b0110011001101010 '
#320000000
0!
b0110011001101010 #
0$
b0110011001101010 &
#325000000
1!
1$
b0111101011100101 '
#330000000
0!
b0111101011100101 #
0$
b0111101011100101 &
#335000000
1!
1$
b1000111101100000 '
#340000000
0!
b1000111101100000 #
0$
b1000111101100000 &
#345000000
1!
1$
b1010001111011011 '
#350000000
0!
b1010001111011011 #
0$
b1010001111011011 &
#355000000
1!
1$
b1011100001010110 '
#360000000
0!
b1011100001010110 #
0$
b1011100001010110 &
#365000000
1!
1$
b1100110011010001 '
#370000000
0!
b1100110011010001 #
0$
b1100110011010001 &
#375000000
1!
1$
b1110000101001100 '
#380000000
0!
b1110000101001100 #
0$
b1110000101001100 &
#385000000
1!
1$
b1111010111000111 '
#390000000
0!
b1111010111000111 #
0$
b1111010111000111 &
#395000000
1!
1$
b0000101001000010 '
#400000000
0!
b0000101001000010 #
0$
b0000101001000010 &
#405000000
1!
1$
b0001111010111101 '
#410000000
0!
b0001111010111101 #
0$
b0001111010111101 &
#415000000
1!
1$
b0011001100111000 '
#420000000
0!
b0011001100111000 #
0$
b0011001100111000 &
#425000000
1!
1$
b0100011110110011 '
#430000000
0!
b0100011110110011 #
0$
b0100011110110011 &
#435000000
1!
1$
b0101110000101110 '
#440000000
0!
b0101110000101110 #
0$
b0101110000101110 &
#445000000
1!
1$
b0111000010101001 '
#450000000
0!
b0111000010101001 #
0$
b0111000010101001 &
#455000000
1!
1$
b1000010100100100 '
#460000000
0!
b1000010100100100 #
0$
b1000010100100100 &
#465000000
1!
1$
b1001100110011111 '
#470000000
0!
b1001100110011111 #
0$
b1001100110011111 &
#475000000
1!
1$
b1010111000011010 '
#480000000
0!
b1010111000011010 #
0$
b1010111000011010 &
#485000000
1!
1$
b1100001010010101 '
#490000000
0!
b1100001010010101 #
0$
b1100001010010101 &
#495000000
1!
1$
b1101011100010000 '
#500000000
0!
b1101011100010000 #
0$
b1101011100010000 &
#505000000
1!
1$
b1110101110001011 '
#510000000
0!
b1110101110001011 #
0$
b1110101110001011 &
#515000000
1!
1$
b0000000000000110 '
#520000000
0!
b0000000000000110 #
0$
b0000000000000110 &
#525000000
1!
1$
b0001010010000001 '
#530000000
0!
b0001010010000001 #
0$
b0001010010000001 &
#535000000
1!
1$
b0010100011111100 '
#540000000
0!
b0010100011111100 #
0$
b0010100011111100 &
#545000000
1!
1$
b0011110101110111 '
#550000000
0!
b0011110101110111 #
0$
b0011110101110111 &
#555000000
1!
1$
b0101000111110010 '
#560000000
0!
b0101000111110010 #
0$
b0101000111110010 &
#565000000
1!
1$
b0110011001101101 '
#570000000
0!
b0110011001101101 #
0$
b0110011001101101 &
#575000000
1!
1$
b0111101011101000 '
#580000000
0!
b0111101011101000 #
0$
b0111101011101000 &
#585000000
1!
1$
b1000111101100011 '
#590000000
0!
b1000111101100011 #
0$
b1000111101100011 &
#595000000
1!
1$
b1010001111011110 '
#600000000
0!
b1010001111011110 #
0$
b1010001111011110 &
#605000000
1!
1$
b1011100001011001 '
#610000000
0!
b1011100001011001 #
0$
b1011100001011001 &
#615000000
1!
1$
b1100110011010100 '
#620000000
0!
b1100110011010100 #
0$
b1100110011010100 &
#625000000
1!
1$
b1110000101001111 '
#630000000
0!
b1110000101001111 #
0$
b1110000101001111 &
#635000000
1!
1$
b1111010111001010 '
#640000000
0!
b1111010111001010 #
0$
b1111010111001010 &
#645000000
1!
1$
b0000101001000101 '
#650000000
0!
b0000101001000101 #
0$
b0000101001000101 &
#655000000
1!
1$
b0001111011000000 '
#660000000
0!
b0001111011000000 #
0$
b0001111011000000 &
#665000000
1!
1$
b0011001100111011 '
#670000000
0!
b0011001100111011 #
0$
b0011001100111011 &
#675000000
1!
1$
b0100011110110110 '
#680000000
0!
b0100011110110110 #
0$
b0100011110110110 &
#685000000
1!
1$
b0101110000110001 '
#690000000
0!
b0101110000110001 #
0$
b0101110000110001 &
#695000000
1!
1$
b0111000010101100 '
#700000000
0!
b0111000010101100 #
0$
b0111000010101100 &
#705000000
1!
1$
b1000010100100111 '
#710000000
0!
b1000010100100111 #
0$
b1000010100100111 &
#715000000
1!
1$
b1001100110100010 '
#720000000
0!
b1001100110100010 #
0$
b1001100110100010 &
#725000000
1!
1$
b1010111000011101 '
#730000000
0!
b1010111000011101 #
0$
b1010111000011101 &
#735000000
1!
1$
b1100001010011000 '
#740000000
0!
b1100001010011000 #
0$
b1100001010011000 &
#745000000
1!
1$
b1101011100010011 '
#750000000
0!
b1101011100010011 #
0$
b1101011100010011 &
#755000000
1!
1$
b1110101110001110 '
#760000000
0!
b1110101110001110 #
0$
b1110101110001110 &
#765000000
1!
1$
b0000000000001001 '
#770000000
0!
b0000000000001001 #
0$
b0000000000001001 &
#775000000
1!
1$
b0001010010000100 '
#780000000
0!
b0001010010000100 #
0$
b0001010010000100 &
#785000000
1!
1$
b0010100011111111 '
#790000000
0!
b0010100011111111 #
0$
b0010100011111111 &
#795000000
1!
1$
b0011110101111010 '
#800000000
0!
b0011110101111010 #
0$
b0011110101111010 &
#805000000
1!
1$
b0101000111110101 '
#810000000
0!
b0101000111110101 #
0$
b0101000111110101 &
#815000000
1!
1$
b0110011001110000 '
#820000000
0!
b0110011001110000 #
0$
b0110011001110000 &
#825000000
1!
1$
b0111101011101011 '
#830000000
0!
b0111101011101011 #
0$
b0111101011101011 &
#835000000
1!
1$
b1000111101100110 '
#840000000
0!
b1000111101100110 #
0$
b1000111101100110 &
#845000000
1!
1$
b1010001111100001 '
#850000000
0!
b1010001111100001 #
0$
b1010001111100001 &
#855000000
1!
1$
b1011100001011100 '
#860000000
0!
b1011100001011100 #
0$
b1011100001011100 &
#865000000
1!
1$
b1100110011010111 '
#870000000
0!
b1100110011010111 #
0$
b1100110011010111 &
#875000000
1!
1$
b1110000101010010 '
#880000000
0!
b1110000101010010 #
0$
b1110000101010010 &
#885000000
1!
1$
b1111010111001101 '
#890000000
0!
b1111010111001101 #
0$
b1111010111001101 &
#895000000
1!
1$
b0000101001001000 '
#900000000
0!
b0000101001001000 #
0$
b0000101001001000 &
#905000000
1!
1$
b0001111011000011 '
#910000000
0!
b0001111011000011 #
0$
b0001111011000011 &
#915000000
1!
1$
b0011001100111110 '
#920000000
0!
b0011001100111110 #
0$
b0011001100111110 &
#925000000
1!
1$
b0100011110111001 '
#930000000
0!
b0100011110111001 #
0$
b0100011110111001 &
#935000000
1!
1$
b0101110000110100 '
#940000000
0!
b0101110000110100 #
0$
b0101110000110100 &
#945000000
1!
1$
b0111000010101111 '
#950000000
0!
b0111000010101111 #
0$
b0111000010101111 &
#955000000
1!
1$
b1000010100101010 '
#960000000
0!
b1000010100101010 #
0$
b1000010100101010 &
#965000000
1!
1$
b1001100110100101 '
#970000000
0!
b1001100110100101 #
0$
b1001100110100101 &
#975000000
1!
1$
b1010111000100000 '
#980000000
0!
b1010111000100000 #
0$
b1010111000100000 &
#985000000
1!
1$
b1100001010011011 '
#990000000
0!
b1100001010011011 #
0$
b1100001010011011 &
#995000000
1!
1$
b1101011100010110 '
#1000000000
0!
b1101011100010110 #
0$
b1101011100010110 &
