HDL/rtl/cordic_pipeline.vhd
library ieee;
use ieee.std_logic_1164.all;
use ieee.numeric_std.all;

use work.cordic_constants.all;

entity cordic_pipeline is
    generic(
        N             : integer := 16; -- Number of iterations of the CORDIC algorithim
        K_INV         : integer := 19898; -- Inverse of scaling constant ~1/1.64676025786
        UPPER_BOUND   : integer := 16384; -- Upper angle limit (pi/2 normalized by pi)
        LOWER_BOUND   : integer := -16384; -- Lower angle limit (-pi/2 normalized by pi)
        ANGLE_WIDTH   : integer := 16 -- Bit width of the angles
    );

    port(
        -- Logic Signals In
        clk           : in std_logic;
        reset         : in std_logic;
        angle_pi_norm : in std_logic_vector(ANGLE_WIDTH -1 downto 0);
        
        -- Logic Signals Out
        I_val     : out std_logic_vector(ANGLE_WIDTH -1 downto 0);
        Q_val     : out std_logic_vector(ANGLE_WIDTH -1 downto 0);

        -- Control Signals In
        in_valid   : in  std_logic;

        -- Control Signals Out
        out_valid  : out std_logic
    );
end cordic_pipeline;

architecture rtl of cordic_pipeline is
    type signed_arr_ANGLE_WIDTH_bit is array (natural range <>) of
        signed(ANGLE_WIDTH -1 downto 0);
    
    type logic_arr is array (natural range <>) of
        std_logic;

    -- Initial Stage Internal Logic
    signal g_upper                      : std_logic; -- Input angle is greater than defined upper bound (UPPER_BOUND)
    signal l_lower                      : std_logic; -- Input angle is less than defined lower bound (LOWER_BOUND)
    signal sel                          : std_logic_vector(1 downto 0);
    signal neg_cos                      : std_logic;
    signal lower_bound_angle_shft_wide  : signed(ANGLE_WIDTH downto 0); -- Widened to accomadate bit shift
    signal upper_bound_angle_shft_wide  : signed(ANGLE_WIDTH downto 0); -- Widened to accomadate bit shift
    signal lower_bound_angle_shft       : signed(ANGLE_WIDTH -1 downto 0);
    signal upper_bound_angle_shft       : signed(ANGLE_WIDTH -1 downto 0);

    -- Inital Stage Logic Outputs
    signal angle_pi_norm_corrected      : signed(ANGLE_WIDTH -1 downto 0); -- Angle wrapped into correct quadrant

    -- Pipeline Outputs
    signal I_val_pipeline_out           : signed_arr_ANGLE_WIDTH_bit(0 to N -1);
    signal Q_val_pipeline_out           : signed_arr_ANGLE_WIDTH_bit(0 to N -1);
    signal angle_err_pipeline_out       : signed_arr_ANGLE_WIDTH_bit(0 to N -1);
    
    -- Pipeline Registers
    signal registers_cordic_angle       : signed_arr_ANGLE_WIDTH_bit(0 to N -1);
    signal registers_angle_err          : signed_arr_ANGLE_WIDTH_bit(0 to N -1);
    signal registers_I_vals             : signed_arr_ANGLE_WIDTH_bit(0 to N -1);
    signal registers_Q_vals             : signed_arr_ANGLE_WIDTH_bit(0 to N -1);
    signal registers_neg_cos            : logic_arr(0 to N -1);
    signal registers_out_valid          : logic_arr(0 to N -1);

    -- Pipeline Out Registers
    signal I_val_output_reg             : signed(ANGLE_WIDTH -1 downto 0);
    signal Q_val_output_reg             : signed(ANGLE_WIDTH -1 downto 0);
    signal out_valid_output_reg         : std_logic;
begin

    g_upper <= '1' when to_integer(signed(angle_pi_norm)) > UPPER_BOUND else '0';
    l_lower <= '1' when to_integer(signed(angle_pi_norm)) < LOWER_BOUND else '0';

    sel <= g_upper & l_lower;

    lower_bound_angle_shft_wide <= -resize(signed(angle_pi_norm), 17) + shift_left(to_signed(LOWER_BOUND, 17), 1);
    upper_bound_angle_shft_wide <= -resize(signed(angle_pi_norm), 17) + shift_left(to_signed(UPPER_BOUND, 17), 1);
    lower_bound_angle_shft <= resize(lower_bound_angle_shft_wide, lower_bound_angle_shft'length);
    upper_bound_angle_shft <= resize(upper_bound_angle_shft_wide, upper_bound_angle_shft'length);

    process(angle_pi_norm, lower_bound_angle_shft, 
            upper_bound_angle_shft, sel)
    begin
        case sel is
            when "00"   => angle_pi_norm_corrected <= signed(angle_pi_norm);
            when "01"   => angle_pi_norm_corrected <= lower_bound_angle_shft;
            when "10"   => angle_pi_norm_corrected <= upper_bound_angle_shft;
            when others => angle_pi_norm_corrected <= (others => '0'); -- Not a possible state
        end case;
    end process;

    neg_cos <= g_upper or l_lower;

    gen_modules : for i in 0 to N - 1 generate
    begin
        process(clk)
        begin
            if rising_edge(clk) then
                if reset = '1' then -- If module is reset
                    registers_cordic_angle(i) <= CORDIC_ANGLES(i);
                    registers_angle_err(i)    <= (others => '0');
                    registers_I_vals(i)       <= (others => '0');
                    registers_Q_vals(i)       <= (others => '0');
                    registers_neg_cos(i)      <= '0';
                    registers_out_valid(i)    <= '0';
                else
                    if i = 0 then -- These registers wire into initial stage of pipeline
                        if in_valid = '0' then -- Input into pipeline must be valid
                            registers_angle_err(i) <= (others => '0');
                            registers_I_vals(i)    <= (others => '0');
                            registers_Q_vals(i)    <= (others => '0');
                            registers_neg_cos(i)   <= '0';
                            registers_out_valid(i) <= '0';
                        else
                            registers_angle_err(i) <= angle_pi_norm_corrected; -- Initial corrected angle
                            registers_I_vals(i)    <= to_signed(K_INV, registers_I_vals(i)'length); -- Initial I val
                            registers_Q_vals(i)    <= (others => '0'); -- Initial Q val
                            registers_neg_cos(i)   <= neg_cos;
                            registers_out_valid(i) <= '1';
                        end if;
                    else -- Pipeline registers wired to a previous pipeline stage
                        registers_angle_err(i) <= angle_err_pipeline_out(i -1);
                        registers_I_vals(i)    <= I_val_pipeline_out(i -1);
                        registers_Q_vals(i)    <= Q_val_pipeline_out(i -1);
                        registers_neg_cos(i)   <= registers_neg_cos(i -1);
                        registers_out_valid(i) <= registers_out_valid(i -1);
                    end if;
                end if;
            end if;

        end process;
        
        process(all)
        begin
            if registers_angle_err(i) > 0 then
                I_val_pipeline_out(i)     <= registers_I_vals(i) + shift_right(registers_Q_vals(i), i);
                Q_val_pipeline_out(i)     <= registers_Q_vals(i) - shift_right(registers_I_vals(i), i);
                angle_err_pipeline_out(i) <= registers_angle_err(i) - registers_cordic_angle(i);
            else
                I_val_pipeline_out(i)     <= registers_I_vals(i) - shift_right(registers_Q_vals(i), i);
                Q_val_pipeline_out(i)     <= registers_Q_vals(i) + shift_right(registers_I_vals(i), i);
                angle_err_pipeline_out(i) <= registers_angle_err(i) + registers_cordic_angle(i);
            end if;
        end process;
    end generate gen_modules;

    process(clk)
    begin
        if rising_edge(clk) then
            I_val_output_reg     <= I_val_pipeline_out(N -1);
            Q_val_output_reg     <= Q_val_pipeline_out(N -1);
            out_valid_output_reg <= registers_out_valid(N -1);
        end if;
    end process;

    I_val     <= std_logic_vector(I_val_output_reg) when registers_neg_cos(N -1) = '0'
                 else std_logic_vector(-I_val_output_reg);
    Q_val     <= std_logic_vector(Q_val_output_reg);
    out_valid <= out_valid_output_reg;


end architecture;

HDL/tb/cordic_pipeline_tb.vhd
library ieee;
use ieee.std_logic_1164.all;
use ieee.numeric_std.all;

entity cordic_pipeline_tb is
end entity cordic_pipeline_tb;

architecture sim of cordic_pipeline_tb is

    constant CLK_PERIOD  : time    := 10 ns;
    constant ANGLE_WIDTH : integer := 16;
    constant N           : integer := 15;
    constant PHASE_INCR  : integer := 5243;

    signal clk           : std_logic := '0';
    signal reset         : std_logic := '0';

    signal angle_in      : std_logic_vector(ANGLE_WIDTH -1 downto 0);

    signal I_val_out     : std_logic_vector(ANGLE_WIDTH -1 downto 0);
    signal Q_val_out     : std_logic_vector(ANGLE_WIDTH -1 downto 0);

    signal in_valid      : std_logic;
    signal out_valid     : std_logic;

begin

    -- Device under test
    dut : entity work.cordic_pipeline
        generic map (
            N           => N,
            ANGLE_WIDTH => ANGLE_WIDTH
        )
        port map (
            clk           => clk,
            reset         => reset,
            angle_pi_norm => angle_in,
            I_val         => I_val_out,
            Q_val         => Q_val_out,
            in_valid      => in_valid,
            out_valid     => out_valid
        );

    -- Clock generator
    clk_process : process
    begin
        while true loop
            clk <= '0';
            wait for CLK_PERIOD / 2;

            clk <= '1';
            wait for CLK_PERIOD / 2;
        end loop;
    end process;

    -- Input stimulus
    stimulus_process : process
    begin

        angle_in <= std_logic_vector(to_signed(4000, 16)); -- Test with 4000

        -- Hold reset active
        reset <= '1';
        wait for 2 * CLK_PERIOD;

        -- Release reset near a clock edge
        wait until falling_edge(clk);
        reset <= '0';

        wait for 2 * CLK_PERIOD; -- Ensure no output before in_valid = '1'
        in_valid <= '1';

        wait;

    end process;

end architecture sim;

HDL/waveform.vcd
$date
  Mon Aug  3 20:24:33 2026
$end
$version
  GHDL v0
$end
$timescale
  1 fs
$end
$scope module standard $end
$upscope $end
$scope module textio $end
$upscope $end
$scope module std_logic_1164 $end
$upscope $end
$scope module numeric_std $end
$upscope $end
$scope module cordic_constants $end
$upscope $end
$scope module cordic_pipeline_tb $end
$var reg 1 ! clk $end
$var reg 1 " reset $end
$var reg 16 # angle_in[15:0] $end
$var reg 16 $ i_val_out[15:0] $end
$var reg 16 % q_val_out[15:0] $end
$var reg 1 & in_valid $end
$var reg 1 ' out_valid $end
$scope module dut $end
$var reg 1 ( clk $end
$var reg 1 ) reset $end
$var reg 16 * angle_pi_norm[15:0] $end
$var reg 16 + i_val[15:0] $end
$var reg 16 , q_val[15:0] $end
$var reg 1 - in_valid $end
$var reg 1 . out_valid $end
$var reg 1 / g_upper $end
$var reg 1 0 l_lower $end
$var reg 2 1 sel[1:0] $end
$var reg 1 2 neg_cos $end
$var reg 17 3 lower_bound_angle_shft_wide[16:0] $end
$var reg 17 4 upper_bound_angle_shft_wide[16:0] $end
$var reg 16 5 lower_bound_angle_shft[15:0] $end
$var reg 16 6 upper_bound_angle_shft[15:0] $end
$var reg 16 7 angle_pi_norm_corrected[15:0] $end
$comment i_val_pipeline_out is not handled $end
$comment q_val_pipeline_out is not handled $end
$comment angle_err_pipeline_out is not handled $end
$comment registers_cordic_angle is not handled $end
$comment registers_angle_err is not handled $end
$comment registers_i_vals is not handled $end
$comment registers_q_vals is not handled $end
$var reg 15 8 registers_neg_cos[0:14] $end
$var reg 15 9 registers_out_valid[0:14] $end
$var reg 16 : i_val_output_reg[15:0] $end
$var reg 16 ; q_val_output_reg[15:0] $end
$var reg 1 < out_valid_output_reg $end
$scope module gen_modules(0) $end
$upscope $end
$scope module gen_modules(1) $end
$upscope $end
$scope module gen_modules(2) $end
$upscope $end
$scope module gen_modules(3) $end
$upscope $end
$scope module gen_modules(4) $end
$upscope $end
$scope module gen_modules(5) $end
$upscope $end
$scope module gen_modules(6) $end
$upscope $end
$scope module gen_modules(7) $end
$upscope $end
$scope module gen_modules(8) $end
$upscope $end
$scope module gen_modules(9) $end
$upscope $end
$scope module gen_modules(10) $end
$upscope $end
$scope module gen_modules(11) $end
$upscope $end
$scope module gen_modules(12) $end
$upscope $end
$scope module gen_modules(13) $end
$upscope $end
$scope module gen_modules(14) $end
$upscope $end
$upscope $end
$upscope $end
$enddefinitions $end
#0
0!
1"
b0000111110100000 #
bXXXXXXXXXXXXXXXX $
bUUUUUUUUUUUUUUUU %
U&
U'
0(
1)
b0000111110100000 *
bXXXXXXXXXXXXXXXX +
bUUUUUUUUUUUUUUUU ,
U-
U.
0/
00
b00 1
02
b10111000001100000 3
b00111000001100000 4
b1111000001100000 5
b0111000001100000 6
b0000111110100000 7
bUUUUUUUUUUUUUUU 8
bUUUUUUUUUUUUUUU 9
bUUUUUUUUUUUUUUUU :
bUUUUUUUUUUUUUUUU ;
U<
#5000000
1!
bXXXXXXXXXXXXXXXX %
1(
bXXXXXXXXXXXXXXXX ,
b000000000000000 8
b000000000000000 9
bXXXXXXXXXXXXXXXX :
bXXXXXXXXXXXXXXXX ;
#10000000
0!
0(
#15000000
1!
b0000000000000000 $
b0000000000000000 %
0'
1(
b0000000000000000 +
b0000000000000000 ,
0.
b0000000000000000 :
b0000000000000000 ;
0<
#20000000
0!
0"
0(
0)
#25000000
1!
1(
b100000000000000 9
#30000000
0!
0(
#35000000
1!
1(
b110000000000000 9
#40000000
0!
1&
0(
1-
#45000000
1!
1(
b111000000000000 9
#50000000
0!
0(
#55000000
1!
1(
b111100000000000 9
#60000000
0!
0(
#65000000
1!
1(
b111110000000000 9
#70000000
0!
0(
#75000000
1!
1(
b111111000000000 9
#80000000
0!
0(
#85000000
1!
1(
b111111100000000 9
#90000000
0!
0(
#95000000
1!
1(
b111111110000000 9
#100000000
0!
0(
#105000000
1!
1(
b111111111000000 9
#110000000
0!
0(
#115000000
1!
1(
b111111111100000 9
#120000000
0!
0(
#125000000
1!
1(
b111111111110000 9
#130000000
0!
0(
#135000000
1!
1(
b111111111111000 9
#140000000
0!
0(
#145000000
1!
1(
b111111111111100 9
#150000000
0!
0(
#155000000
1!
1(
b111111111111110 9
#160000000
0!
0(
#165000000
1!
1(
b111111111111111 9
#170000000
0!
0(
#175000000
1!
b1000001110100110 $
b1011001111010010 %
1'
1(
b1000001110100110 +
b1011001111010010 ,
1.
b1000001110100110 :
b1011001111010010 ;
1<
